{"note":"This file is an internal implementation detail to speed up HTML report generation. Its format can change at any time. You might be looking for the JSON report: https://coverage.rtfd.io/cmd.html#cmd-json","format":5,"version":"7.6.1","globals":"b4a597f903032b40fcc6f4131c613906","files":{"z_c79324c3b0d4d28c___main___py":{"hash":"3c8bf5b5e313bddf276f7bc8c8aee61c","index":{"url":"z_c79324c3b0d4d28c___main___py.html","file":"coverage_comment/__main__.py","description":"","nums":{"precision":0,"n_files":1,"n_statements":6,"n_excluded":0,"n_missing":0,"n_branches":2,"n_partial_branches":0,"n_missing_branches":0}}},"z_c79324c3b0d4d28c_activity_py":{"hash":"9ef818c43047760c7f6d618e21a5850b","index":{"url":"z_c79324c3b0d4d28c_activity_py.html","file":"coverage_comment/activity.py","description":"","nums":{"precision":0,"n_files":1,"n_statements":11,"n_excluded":0,"n_missing":0,"n_branches":6,"n_partial_branches":0,"n_missing_branches":0}}},"z_c79324c3b0d4d28c_badge_py":{"hash":"23dca31f338045efe62d004fdcd7bf70","index":{"url":"z_c79324c3b0d4d28c_badge_py.html","file":"coverage_comment/badge.py","description":"","nums":{"precision":0,"n_files":1,"n_statements":31,"n_excluded":0,"n_missing":0,"n_branches":12,"n_partial_branches":0,"n_missing_branches":0}}},"z_c79324c3b0d4d28c_comment_file_py":{"hash":"311d361cd9f47f2f52a46ff806316648","index":{"url":"z_c79324c3b0d4d28c_comment_file_py.html","file":"coverage_comment/comment_file.py","description":"","nums":{"precision":0,"n_files":1,"n_statements":4,"n_excluded":0,"n_missing":0,"n_branches":0,"n_partial_branches":0,"n_missing_branches":0}}},"z_c79324c3b0d4d28c_communication_py":{"hash":"585a0f10d763eedd49b736dfdda28141","index":{"url":"z_c79324c3b0d4d28c_communication_py.html","file":"coverage_comment/communication.py","description":"","nums":{"precision":0,"n_files":1,"n_statements":8,"n_excluded":0,"n_missing":0,"n_branches":0,"n_partial_branches":0,"n_missing_branches":0}}},"z_c79324c3b0d4d28c_coverage_py":{"hash":"cc7402433b4541c9fb86e72077a8ea39","index":{"url":"z_c79324c3b0d4d28c_coverage_py.html","file":"coverage_comment/coverage.py","description":"","nums":{"precision":0,"n_files":1,"n_statements":120,"n_excluded":0,"n_missing":0,"n_branches":34,"n_partial_branches":0,"n_missing_branches":0}}},"z_c79324c3b0d4d28c_diff_grouper_py":{"hash":"8b783d306f84f60a523b45e5ad417aaf","index":{"url":"z_c79324c3b0d4d28c_diff_grouper_py.html","file":"coverage_comment/diff_grouper.py","description":"","nums":{"precision":0,"n_files":1,"n_statements":12,"n_excluded":0,"n_missing":0,"n_branches":4,"n_partial_branches":0,"n_missing_branches":0}}},"z_c79324c3b0d4d28c_files_py":{"hash":"7c4813f75d9d679360f146ece3e63398","index":{"url":"z_c79324c3b0d4d28c_files_py.html","file":"coverage_comment/files.py","description":"","nums":{"precision":0,"n_files":1,"n_statements":59,"n_excluded":2,"n_missing":0,"n_branches":6,"n_partial_branches":0,"n_missing_branches":0}}},"z_c79324c3b0d4d28c_github_py":{"hash":"db792ac4c6df0c046fda964c91d67db6","index":{"url":"z_c79324c3b0d4d28c_github_py.html","file":"coverage_comment/github.py","description":"","nums":{"precision":0,"n_files":1,"n_statements":118,"n_excluded":0,"n_missing":0,"n_branches":28,"n_partial_branches":0,"n_missing_branches":0}}},"z_c79324c3b0d4d28c_github_client_py":{"hash":"76c565ae8b089e99251d3477bbb92a88","index":{"url":"z_c79324c3b0d4d28c_github_client_py.html","file":"coverage_comment/github_client.py","description":"","nums":{"precision":0,"n_files":1,"n_statements":67,"n_excluded":0,"n_missing":0,"n_branches":14,"n_partial_branches":0,"n_missing_branches":0}}},"z_c79324c3b0d4d28c_groups_py":{"hash":"948aa793ed71b1e376831b070a79281e","index":{"url":"z_c79324c3b0d4d28c_groups_py.html","file":"coverage_comment/groups.py","description":"","nums":{"precision":0,"n_files":1,"n_statements":35,"n_excluded":0,"n_missing":0,"n_branches":11,"n_partial_branches":0,"n_missing_branches":0}}},"z_c79324c3b0d4d28c_log_py":{"hash":"91bb1449cb9a1cb89ff29eda4b211b95","index":{"url":"z_c79324c3b0d4d28c_log_py.html","file":"coverage_comment/log.py","description":"","nums":{"precision":0,"n_files":1,"n_statements":5,"n_excluded":0,"n_missing":0,"n_branches":0,"n_partial_branches":0,"n_missing_branches":0}}},"z_c79324c3b0d4d28c_log_utils_py":{"hash":"c972330f4b8209c89da33c5023d9a161","index":{"url":"z_c79324c3b0d4d28c_log_utils_py.html","file":"coverage_comment/log_utils.py","description":"","nums":{"precision":0,"n_files":1,"n_statements":9,"n_excluded":0,"n_missing":0,"n_branches":0,"n_partial_branches":0,"n_missing_branches":0}}},"z_c79324c3b0d4d28c_main_py":{"hash":"492bce6d14465faa02f83031f31b6985","index":{"url":"z_c79324c3b0d4d28c_main_py.html","file":"coverage_comment/main.py","description":"","nums":{"precision":0,"n_files":1,"n_statements":131,"n_excluded":0,"n_missing":0,"n_branches":22,"n_partial_branches":0,"n_missing_branches":0}}},"z_c79324c3b0d4d28c_settings_py":{"hash":"9cd80064c00daa20e9847756102464e8","index":{"url":"z_c79324c3b0d4d28c_settings_py.html","file":"coverage_comment/settings.py","description":"","nums":{"precision":0,"n_files":1,"n_statements":119,"n_excluded":0,"n_missing":0,"n_branches":50,"n_partial_branches":0,"n_missing_branches":0}}},"z_c79324c3b0d4d28c_storage_py":{"hash":"72ae3cd30690ea9662d1bc0f14eefdd8","index":{"url":"z_c79324c3b0d4d28c_storage_py.html","file":"coverage_comment/storage.py","description":"","nums":{"precision":0,"n_files":1,"n_statements":69,"n_excluded":0,"n_missing":0,"n_branches":10,"n_partial_branches":0,"n_missing_branches":0}}},"z_c79324c3b0d4d28c_subprocess_py":{"hash":"02397ecb10a860bc2231b059daeab96c","index":{"url":"z_c79324c3b0d4d28c_subprocess_py.html","file":"coverage_comment/subprocess.py","description":"","nums":{"precision":0,"n_files":1,"n_statements":26,"n_excluded":0,"n_missing":0,"n_branches":0,"n_partial_branches":0,"n_missing_branches":0}}},"z_c79324c3b0d4d28c_template_py":{"hash":"5dfd37b26e63962376cab0e26ad2bb11","index":{"url":"z_c79324c3b0d4d28c_template_py.html","file":"coverage_comment/template.py","description":"","nums":{"precision":0,"n_files":1,"n_statements":117,"n_excluded":14,"n_missing":0,"n_branches":28,"n_partial_branches":0,"n_missing_branches":0}}}}}